pdfmask/__init__.py
pdfmask/mask.py
pdfmask/mask_gen.py
pdfmask-0.2.0.dist-info/LICENSE
pdfmask-0.2.0.dist-info/METADATA
pdfmask-0.2.0.dist-info/WHEEL
pdfmask-0.2.0.dist-info/entry_points.txt
pdfmask-0.2.0.dist-info/top_level.txt
pdfmask-0.2.0.dist-info/RECORD
