Metadata-Version: 2.1
Name: pdfmask
Version: 0.2.0
Summary: A command line tool for masking the content area in PDF
Home-page: https://github.com/hiroshi-matsuda/pdfmask
Author: Hiroshi Matsuda
Author-email: hmtd223@gmail.com
License: BSD-3-Clause
Platform: UNKNOWN
Requires-Python: >=3.6
License-File: LICENSE
Requires-Dist: reportlab (<3.7.0,>=3.6.11)
Requires-Dist: PyPDF2 (<2.11.0,>=2.10.3)
